flake8_new_union_types.py
flake8_new_union_types-0.4.1.dist-info/entry_points.txt
flake8_new_union_types-0.4.1.dist-info/LICENSE
flake8_new_union_types-0.4.1.dist-info/WHEEL
flake8_new_union_types-0.4.1.dist-info/METADATA
flake8_new_union_types-0.4.1.dist-info/RECORD
