Metadata-Version: 2.1
Name: flake8-new-union-types
Version: 0.4.1
Summary: Flake8 plugin to enforce the new Union and Optional annotation syntax defined in PEP 604
Home-page: https://github.com/xome4ok/flake8-new-union-types
License: MIT
Keywords: flake8,flake8-plugin,linting,linter,code quality,pep604,pep 604,syntax
Author: Dmitriy Pryanichnikov
Author-email: dmitrii.prianichnikov@incountry.com
Requires-Python: >=3.8,<4.0
Classifier: Development Status :: 4 - Beta
Classifier: Environment :: Console
Classifier: Framework :: Flake8
Classifier: Intended Audience :: Developers
Classifier: License :: OSI Approved :: MIT License
Classifier: Operating System :: OS Independent
Classifier: Programming Language :: Python
Classifier: Programming Language :: Python :: 3
Classifier: Programming Language :: Python :: 3 :: Only
Classifier: Programming Language :: Python :: 3.10
Classifier: Programming Language :: Python :: 3.8
Classifier: Programming Language :: Python :: 3.9
Classifier: Topic :: Software Development :: Libraries :: Python Modules
Classifier: Topic :: Software Development :: Quality Assurance
Requires-Dist: attrs (>=21.4.0)
Requires-Dist: flake8 (>=3.0.0)
Project-URL: Repository, https://github.com/xome4ok/flake8-new-union-types
